pyhdrh.cpython-310-i386-linux-gnu.so
hdrhistogram-0.10.3.dist-info/AUTHORS
hdrhistogram-0.10.3.dist-info/entry_points.txt
hdrhistogram-0.10.3.dist-info/LICENSE
hdrhistogram-0.10.3.dist-info/top_level.txt
hdrhistogram-0.10.3.dist-info/RECORD
hdrhistogram-0.10.3.dist-info/METADATA
hdrhistogram-0.10.3.dist-info/pbr.json
hdrhistogram-0.10.3.dist-info/WHEEL
hdrh/iterators.py
hdrh/log.py
hdrh/dump.py
hdrh/histogram.py
hdrh/codec.py
hdrh/__init__.py
