Metadata-Version: 2.1
Name: hdrhistogram
Version: 0.10.3
Summary: High Dynamic Range histogram in native python
Home-page: https://github.com/HdrHistogram/HdrHistogram_py
Author: Alec Hothan
Author-email: ahothan@gmail.com
Keywords: hdrhistogram hdr histogram high dynamic range
Classifier: Intended Audience :: Developers
Classifier: Intended Audience :: Information Technology
Classifier: Intended Audience :: System Administrators
Classifier: License :: OSI Approved :: Apache Software License
Classifier: Operating System :: POSIX :: Linux
Classifier: Operating System :: MacOS
Classifier: Programming Language :: Python
Classifier: Programming Language :: Python :: 3
Classifier: Programming Language :: Python :: 3.6
Classifier: Programming Language :: Python :: 3.7
Classifier: Programming Language :: Python :: 3.8
Classifier: Programming Language :: Python :: 3.9
Classifier: Programming Language :: Python :: 3.10
Classifier: Programming Language :: Python :: 3.11
License-File: LICENSE
